MANIFEST.in
setup.py
crispy_semantic_ui.egg-info/PKG-INFO
crispy_semantic_ui.egg-info/SOURCES.txt
crispy_semantic_ui.egg-info/dependency_links.txt
crispy_semantic_ui.egg-info/requires.txt
crispy_semantic_ui.egg-info/top_level.txt
semantic_ui/__init__.py
semantic_ui/__init__.pyc
semantic_ui/apps.py
semantic_ui/apps.pyc
semantic_ui/models.py
semantic_ui/patch.py
semantic_ui/patch.pyc
semantic_ui/__pycache__/__init__.cpython-34.pyc
semantic_ui/__pycache__/apps.cpython-34.pyc
semantic_ui/__pycache__/models.cpython-34.pyc
semantic_ui/__pycache__/patch.cpython-34.pyc
semantic_ui/templates/semantic-ui/betterform.html
semantic_ui/templates/semantic-ui/display_form.html
semantic_ui/templates/semantic-ui/errors.html
semantic_ui/templates/semantic-ui/errors_formset.html
semantic_ui/templates/semantic-ui/field.html
semantic_ui/templates/semantic-ui/multifield.html
semantic_ui/templates/semantic-ui/pagination.html
semantic_ui/templates/semantic-ui/uni_form.html
semantic_ui/templates/semantic-ui/uni_formset.html
semantic_ui/templates/semantic-ui/whole_uni_form.html
semantic_ui/templates/semantic-ui/whole_uni_formset.html
semantic_ui/templates/semantic-ui/layout/baseinput.html
semantic_ui/templates/semantic-ui/layout/buttonholder.html
semantic_ui/templates/semantic-ui/layout/div.html
semantic_ui/templates/semantic-ui/layout/fieldset.html
semantic_ui/templates/semantic-ui/layout/multifield.html
semantic_ui/templates/semantic-ui/layout/radioselect.html
semantic_ui/templatetags/__init__.py
semantic_ui/templatetags/semantic_ui.py
semantic_ui/templatetags/__pycache__/__init__.cpython-34.pyc