Metadata-Version: 1.0
Name: crispy-semantic-ui
Version: 1.0.2
Summary: Semantic UI template pack for crispy forms
Home-page: https://github.com/alexey-grom/crispy-semantic-ui
Author: alxgrmv@gmail.com
Author-email: UNKNOWN
License: UNKNOWN
Platform: UNKNOWN
